HDMI_to_Matrix_FPGA/Test_Project/DVI_RX_Test/src/dvi_rx/DVI_RX_SIM.sv
module DVI_RX_SIM #(
    parameter int H_ACTIVE = 800,
    parameter int H_TOTAL  = 1056,
    parameter int V_ACTIVE = 600,
    parameter int V_TOTAL  = 628
)(
    input  logic clk,       // Input-Takt für Simulation
    input  logic rst_n,

    output logic [3:0] O_pll_phase,
    output logic       O_pll_phase_lock,
    output logic       O_rgb_clk,
    output logic       O_rgb_vs,
    output logic       O_rgb_hs,
    output logic       O_rgb_de,
    output logic [7:0] O_rgb_r,
    output logic [7:0] O_rgb_g,
    output logic [7:0] O_rgb_b
);

    // Lokale Parameter
    localparam int H_SYNC_START = H_ACTIVE + 8;
    localparam int H_SYNC_END   = H_SYNC_START + 8;

    localparam int V_SYNC_START = V_ACTIVE + 1;
    localparam int V_SYNC_END   = V_SYNC_START + 2;


    // Pixelzähler
    int unsigned hcount = 0;
    int unsigned vcount = 0;

    logic pixclk = 0;

    // Pixeltakt (Clock Divider 1:2)
    always_ff @(posedge clk or negedge rst_n) begin
        if (!rst_n)
            pixclk <= 0;
        else
            pixclk <= ~pixclk;
    end

    // Horizontal- & Vertikalzähler
    always_ff @(posedge pixclk or negedge rst_n) begin
        if (!rst_n) begin
            hcount <= 0;
            vcount <= 0;
        end else begin
            if (hcount == H_TOTAL - 1) begin
                hcount <= 0;
                if (vcount == V_TOTAL - 1)
                    vcount <= 0;
                else
                    vcount <= vcount + 1;
            end else begin
                hcount <= hcount + 1;
            end
        end
    end

    // Clock-Ausgang
    always_ff @(posedge clk)
        O_rgb_clk <= pixclk;

    // Video-Synchronisation
    always_comb begin
        O_rgb_de = (hcount < H_ACTIVE) && (vcount < V_ACTIVE);
        O_rgb_hs = (hcount >= H_SYNC_START) && (hcount < H_SYNC_END);
        O_rgb_vs = (vcount >= V_SYNC_START) && (vcount < V_SYNC_END);
    end

    // Farb-Generator (einfaches Testmuster)
    logic [3:0] hcount_region;

    always @(*) begin
        logic [3:0] region;
        region = hcount[9:6];

        if (O_rgb_de) begin
            case (region)
                4'h0: begin O_rgb_r = 8'hFF; O_rgb_g = 8'h00; O_rgb_b = 8'h00; end
                4'h1: begin O_rgb_r = 8'h00; O_rgb_g = 8'hFF; O_rgb_b = 8'h00; end
                4'h2: begin O_rgb_r = 8'h00; O_rgb_g = 8'h00; O_rgb_b = 8'hFF; end
                4'h3: begin O_rgb_r = 8'hFF; O_rgb_g = 8'hFF; O_rgb_b = 8'h00; end
                4'h4: begin O_rgb_r = 8'h00; O_rgb_g = 8'hFF; O_rgb_b = 8'hFF; end
                4'h5: begin O_rgb_r = 8'hFF; O_rgb_g = 8'h00; O_rgb_b = 8'hFF; end
                4'h6: begin O_rgb_r = 8'h80; O_rgb_g = 8'h80; O_rgb_b = 8'h80; end
                default: begin O_rgb_r = 8'h00; O_rgb_g = 8'h00; O_rgb_b = 8'h00; end
            endcase
        end else begin
            O_rgb_r = 8'h00;
            O_rgb_g = 8'h00;
            O_rgb_b = 8'h00;
        end
    end

    // PLL-Signale (konstant simuliert)
    assign O_pll_phase      = 4'd4;  // 90°
    assign O_pll_phase_lock = 1'b1;  // locked

endmodule

HDMI_to_Matrix_FPGA/Test_Project/DVI_RX_Test/src/dvi_rx/DVI_RX_SIM_tb.sv
`timescale 1ns / 1ps

module DVI_RX_SIM_tb;

    // Signale
    logic clk;
    logic rst_n;

    // DVI_RX_SIM Outputs
    logic [3:0] O_pll_phase;
    logic       O_pll_phase_lock;
    logic       O_rgb_clk;
    logic       O_rgb_vs;
    logic       O_rgb_hs;
    logic       O_rgb_de;
    logic [7:0] O_rgb_r;
    logic [7:0] O_rgb_g;
    logic [7:0] O_rgb_b;

    // Taktgenerator: 50 MHz (Periode 20 ns)
    initial clk = 0;
    always #10 clk = ~clk;

    // Reset
    initial begin
        rst_n = 0;
        #100;
        rst_n = 1;
    end

    // Instanz des DUT (kleine Auflösung für schnellen Durchlauf)
    DVI_RX_SIM #(
        .H_ACTIVE(128),
        .H_TOTAL(144),
        .V_ACTIVE(32),
        .V_TOTAL(40)
    ) dut (
        .clk(clk),
        .rst_n(rst_n),
        .O_pll_phase(O_pll_phase),
        .O_pll_phase_lock(O_pll_phase_lock),
        .O_rgb_clk(O_rgb_clk),
        .O_rgb_vs(O_rgb_vs),
        .O_rgb_hs(O_rgb_hs),
        .O_rgb_de(O_rgb_de),
        .O_rgb_r(O_rgb_r),
        .O_rgb_g(O_rgb_g),
        .O_rgb_b(O_rgb_b)
    );

    // Simulationsdauer begrenzen
    initial begin
        #1_000_000;  // 1 ms Simulation (~25 volle Frames bei 25 MHz Pixelclock)
        $finish;
    end

    initial begin
        $dumpfile("DVI_RX_SIM_tb.vcd");
        $dumpvars(0, DVI_RX_SIM_tb);
    end

endmodule

HDMI_to_Matrix_FPGA/Test_Project/DVI_RX_Test/sim/DVI_RX_SIM_tb.vcd
$date
	Wed Apr 16 12:17:38 2025
$end
$version
	Icarus Verilog
$end
$timescale
	1ps
$end
$scope module DVI_RX_SIM_tb $end
$var wire 4 ! O_pll_phase [3:0] $end
$var wire 1 " O_pll_phase_lock $end
$var wire 1 # O_rgb_vs $end
$var wire 8 $ O_rgb_r [7:0] $end
$var wire 1 % O_rgb_hs $end
$var wire 8 & O_rgb_g [7:0] $end
$var wire 1 ' O_rgb_de $end
$var wire 1 ( O_rgb_clk $end
$var wire 8 ) O_rgb_b [7:0] $end
$var reg 1 * clk $end
$var reg 1 + rst_n $end
$scope module dut $end
$var wire 4 , O_pll_phase [3:0] $end
$var wire 1 " O_pll_phase_lock $end
$var wire 1 * clk $end
$var wire 1 + rst_n $end
$var parameter 32 - H_ACTIVE $end
$var parameter 32 . H_SYNC_END $end
$var parameter 32 / H_SYNC_START $end
$var parameter 32 0 H_TOTAL $end
$var parameter 32 1 V_ACTIVE $end
$var parameter 32 2 V_SYNC_END $end
$var parameter 32 3 V_SYNC_START $end
$var parameter 32 4 V_TOTAL $end
$var reg 8 5 O_rgb_b [7:0] $end
$var reg 1 ( O_rgb_clk $end
$var reg 1 ' O_rgb_de $end
$var reg 8 6 O_rgb_g [7:0] $end
$var reg 1 % O_rgb_hs $end
$var reg 8 7 O_rgb_r [7:0] $end
$var reg 1 # O_rgb_vs $end
$var reg 1 8 pixclk $end
$var reg 32 9 hcount [31:0] $end
$var reg 32 : vcount [31:0] $end
$scope begin $unm_blk_26 $end
$var reg 4 ; region [3:0] $end
$upscope $end
$upscope $end
$upscope $end
$enddefinitions $end
$comment Show the parameter values. $end
$dumpall
b101000 4
b100001 3
b100011 2
b100000 1
b10010000 0
b10001000 /
b10010000 .
b10000000 -
$end
#0
$dumpvars
b0 ;
b0 :
b0 9
08
b11111111 7
b0 6
b0 5
b100 ,
0+
0*
b0 )
x(
1'
b0 &
0%
b11111111 $
0#
1"
b100 !
$end
#10000
0(
1*
#20000
0*
#30000
1*
#40000
0*
#50000
1*
#60000
0*
#70000
1*
#80000
0*
#90000
1*
#100000
0*
1+
#110000
b1 9
18
1*
#120000
0*
#130000
1(
08
1*
#140000
0*
#150000
b10 9
0(
18
1*
#160000
0*
#170000
1(
08
1*
#180000
0*
#190000
b11 9
0(
18
1*
#200000
0*
#210000
1(
08
1*
#220000
0*
#230000
b100 9
0(
18
1*
#240000
0*
#250000
1(
08
1*
#260000
0*
#270000
b101 9
0(
18
1*
#280000
0*
#290000
1(
08
1*
#300000
0*
#310000
b110 9
0(
18
1*
#320000
0*
#330000
1(
08
1*
#340000
0*
#350000
b111 9
0(
18
1*
#360000
0*
#370000
1(
08
1*
#380000
0*
#390000
b1000 9
0(
18
1*
#400000
0*
#410000
1(
08
1*
#420000
0*
#430000
b1001 9
0(
18
1*
#440000
0*
#450000
1(
08
1*
#460000
0*
#470000
b1010 9
0(
18
1*
#480000
0*
#490000
1(
08
1*
#500000
0*
#510000
b1011 9
0(
18
1*
#520000
0*
#530000
1(
08
1*
#540000
0*
#550000
b1100 9
0(
18
1*
#560000
0*
#570000
1(
08
1*
#580000
0*
#590000
b1101 9
0(
18
1*
#600000
0*
#610000
1(
08
1*
#620000
0*
#630000
b1110 9
0(
18
1*
#640000
0*
#650000
1(
08
1*
#660000
0*
#670000
b1111 9
0(
18
1*
#680000
0*
#690000
1(
08
1*
#700000
0*
#710000
b10000 9
0(
18
1*
#720000
0*
#730000
1(
08
1*
#740000
0*
#750000
b10001 9
0(
18
1*
#760000
0*
#770000
1(
08
1*
#780000
0*
#790000
b10010 9
0(
18
1*
#800000
0*
#810000
1(
08
1*
#820000
0*
#830000
b10011 9
0(
18
1*
#840000
0*
#850000
1(
08
1*
#860000
0*
#870000
b10100 9
0(
18
1*
#880000
0*
#890000
1(
08
1*
#900000
0*
#910000
b10101 9
0(
18
1*
#920000
0*
#930000
1(
08
1*
#940000
0*
#950000
b10110 9
0(
18
1*
#960000
0*
#970000
1(
08
1*
#980000
0*
#990000
b10111 9
0(
18
1*
#1000000
0*
#1010000
1(
08
1*
#1020000
0*
#1030000
b11000 9
0(
18
1*
#1040000
0*
#1050000
1(
08
1*
#1060000
0*
#1070000
b11001 9
0(
18
1*
#1080000
0*
#1090000
1(
08
1*
#1100000
0*
#1110000
b11010 9
0(
18
1*
#1120000
0*
#1130000
1(
08
1*
#1140000
0*
#1150000
b11011 9
0(
18
1*
#1160000
0*
#1170000
1(
08
1*
#1180000
0*
#1190000
b11100 9
0(
18
1*
#1200000
0*
#1210000
1(
08
1*
#1220000
0*
#1230000
b11101 9
0(
18
1*
#1240000
0*
#1250000
1(
08
1*
#1260000
0*
#1270000
b11110 9
0(
18
1*
#1280000
0*
#1290000
1(
08
1*
#1300000
0*
#1310000
b11111 9
0(
18
1*
#1320000
0*
#1330000
1(
08
1*
#1340000
0*
#1350000
b100000 9
0(
18
1*
#1360000
0*
#1370000
1(
08
1*
#1380000
0*
#1390000
b100001 9
0(
18
1*
#1400000
0*
#1410000
1(
08
1*
#1420000
0*
#1430000
b100010 9
0(
18
1*
#1440000
0*
#1450000
1(
08
1*
#1460000
0*
#1470000
b100011 9
0(
18
1*
#1480000
0*
#1490000
1(
08
1*
#1500000
0*
#1510000
b100100 9
0(
18
1*
#1520000
0*
#1530000
1(
08
1*
#1540000
0*
#1550000
b100101 9
0(
18
1*
#1560000
0*
#1570000
1(
08
1*
#1580000
0*
#1590000
b100110 9
0(
18
1*
#1600000
0*
#1610000
1(
08
1*
#1620000
0*
#1630000
b100111 9
0(
18
1*
#1640000
0*
#1650000
1(
08
1*
#1660000
0*
#1670000
b101000 9
0(
18
1*
#1680000
0*
#1690000
1(
08
1*
#1700000
0*
#1710000
b101001 9
0(
18
1*
#1720000
0*
#1730000
1(
08
1*
#1740000
0*
#1750000
b101010 9
0(
18
1*
#1760000
0*
#1770000
1(
08
1*
#1780000
0*
#1790000
b101011 9
0(
18
1*
#1800000
0*
#1810000
1(
08
1*
#1820000
0*
#1830000
b101100 9
0(
18
1*
#1840000
0*
#1850000
1(
08
1*
#1860000
0*
#1870000
b101101 9
0(
18
1*
#1880000
0*
#1890000
1(
08
1*
#1900000
0*
#1910000
b101110 9
0(
18
1*
#1920000
0*
#1930000
1(
08
1*
#1940000
0*
#1950000
b101111 9
0(
18
1*
#1960000
0*
#1970000
1(
08
1*
#1980000
0*
#1990000
b110000 9
0(
18
1*
#2000000
0*
#2010000
1(
08
1*
#2020000
0*
#2030000
b110001 9
0(
18
1*
#2040000
0*
#2050000
1(
08
1*
#2060000
0*
#2070000
b110010 9
0(
18
1*
#2080000
0*
#2090000
1(
08
1*
#2100000
0*
#2110000
b110011 9
0(
18
1*
#2120000
0*
#2130000
1(
08
1*
#2140000
0*
#2150000
b110100 9
0(
18
1*
#2160000
0*
#2170000
1(
08
1*
#2180000
0*
#2190000
b110101 9
0(
18
1*
#2200000
0*
#2210000
1(
08
1*
#2220000
0*
#2230000
b110110 9
0(
18
1*
#2240000
0*
#2250000
1(
08
1*
#2260000
0*
#2270000
b110111 9
0(
18
1*
#2280000
0*
#2290000
1(
08
1*
#2300000
0*
#2310000
b111000 9
0(
18
1*
#2320000
0*
#2330000
1(
08
1*
#2340000
0*
#2350000
b111001 9
0(
18
1*
#2360000
0*
#2370000
1(
08
1*
#2380000
0*
#2390000
b111010 9
0(
18
1*
#2400000
0*
#2410000
1(
08
1*
#2420000
0*
#2430000
b111011 9
0(
18
1*
#2440000
0*
#2450000
1(
08
1*
#2460000
0*
#2470000
b111100 9
0(
18
1*
#2480000
0*
#2490000
1(
08
1*
#2500000
0*
#2510000
b111101 9
0(
18
1*
#2520000
0*
#2530000
1(
08
1*
#2540000
0*
#2550000
b111110 9
0(
18
1*
#2560000
0*
#2570000
1(
08
1*
#2580000
0*
#2590000
b111111 9
0(
18
1*
#2600000
0*
#2610000
1(
08
1*
#2620000
0*
#2630000
b11111111 &
b11111111 6
b0 $
b0 7
b1 ;
b1000000 9
0(
18
1*
#2640000
0*
#2650000
1(
08
1*
#2660000
0*
#2670000
b1000001 9
0(
18
1*
#2680000
0*
#2690000
1(
08
1*
#2700000
0*
#2710000
b1000010 9
0(
18
1*
#2720000
0*
#2730000
1(
08
1*
#2740000
0*
#2750000
b1000011 9
0(
18
1*
#2760000
0*
#2770000
1(
08
1*
#2780000
0*
#2790000
b1000100 9
0(
18
1*
#2800000
0*
#2810000
1(
08
1*
#2820000
0*
#2830000
b1000101 9
0(
18
1*
#2840000
0*
#2850000
1(
08
1*
#2860000
0*
#2870000
b1000110 9
0(
18
1*
#2880000
0*
#2890000
1(
08
1*
#2900000
0*
#2910000
b1000111 9
0(
18
1*
#2920000
0*
#2930000
1(
08
1*
#2940000
0*
#2950000
b1001000 9
0(
18
1*
#2960000
0*
#2970000
1(
08
1*
#2980000
0*
#2990000
b1001001 9
0(
18
1*
#3000000
0*
#3010000
1(
08
1*
#3020000
0*
#3030000
b1001010 9
0(
18
1*
#3040000
0*
#3050000
1(
08
1*
#3060000
0*
#3070000
b1001011 9
0(
18
1*
#3080000
0*
#3090000
1(
08
1*
#3100000
0*
#3110000
b1001100 9
0(
18
1*
#3120000
0*
#3130000
1(
08
1*
#3140000
0*
#3150000
b1001101 9
0(
18
1*
#3160000
0*
#3170000
1(
08
1*
#3180000
0*
#3190000
b1001110 9
0(
18
1*
#3200000
0*
#3210000
1(
08
1*
#3220000
0*
#3230000
b1001111 9
0(
18
1*
#3240000
0*
#3250000
1(
08
1*
#3260000
0*
#3270000
b1010000 9
0(
18
1*
#3280000
0*
#3290000
1(
08
1*
#3300000
0*
#3310000
b1010001 9
0(
18
1*
#3320000
0*
#3330000
1(
08
1*
#3340000
0*
#3350000
b1010010 9
0(
18
1*
#3360000
0*
#3370000
1(
08
1*
#3380000
0*
#3390000
b1010011 9
0(
18
1*
#3400000
0*
#3410000
1(
08
1*
#3420000
0*
#3430000
b1010100 9
0(
18
1*
#3440000
0*
#3450000
1(
08
1*
#3460000
0*
#3470000
b1010101 9
0(
18
1*
#3480000
0*
#3490000
1(
08
1*
#3500000
0*
#3510000
b1010110 9
0(
18
1*
#3520000
0*
#3530000
1(
08
1*
#3540000
0*
#3550000
b1010111 9
0(
18
1*
#3560000
0*
#3570000
1(
08
1*
#3580000
0*
#3590000
b1011000 9
0(
18
1*
#3600000
0*
#3610000
1(
08
1*
#3620000
0*
#3630000
b1011001 9
0(
18
1*
#3640000
0*
#3650000
1(
08
1*
#3660000
0*
#3670000
b1011010 9
0(
18
1*
#3680000
0*
#3690000
1(
08
1*
#3700000
0*
#3710000
b1011011 9
0(
18
1*
#3720000
0*
#3730000
1(
08
1*
#3740000
0*
#3750000
b1011100 9
0(
18
1*
#3760000
0*
#3770000
1(
08
1*
#3780000
0*
#3790000
b1011101 9
0(
18
1*
#3800000
0*
#3810000
1(
08
1*
#3820000
0*
#3830000
b1011110 9
0(
18
1*
#3840000
0*
#3850000
1(
08
1*
#3860000
0*
#3870000
b1011111 9
0(
18
1*
#3880000
0*
#3890000
1(
08
1*
#3900000
0*
#3910000
b1100000 9
0(
18
1*
#3920000
0*
#3930000
1(
08
1*
#3940000
0*
#3950000
b1100001 9
0(
18
1*
#3960000
0*
#3970000
1(
08
1*
#3980000
0*
#3990000
b1100010 9
0(
18
1*
#4000000
0*
#4010000
1(
08
1*
#4020000
0*
#4030000
b1100011 9
0(
18
1*
#4040000
0*
#4050000
1(
08
1*
#4060000
0*
#4070000
b1100100 9
0(
18
1*
#4080000
0*
#4090000
1(
08
1*
#4100000
0*
#4110000
b1100101 9
0(
18
1*
#4120000
0*
#4130000
1(
08
1*
#4140000
0*
#4150000
b1100110 9
0(
18
1*
#4160000
0*
#4170000
1(
08
1*
#4180000
0*
#4190000
b1100111 9
0(
18
1*
#4200000
0*
#4210000
1(
08
1*
#4220000
0*
#4230000
b1101000 9
0(
18
1*
#4240000
0*
#4250000
1(
08
1*
#4260000
0*
#4270000
b1101001 9
0(
18
1*
#4280000
0*
#4290000
1(
08
1*
#4300000
0*
#4310000
b1101010 9
0(
18
1*
#4320000
0*
#4330000
1(
08
1*
#4340000
0*
#4350000
b1101011 9
0(
18
1*
#4360000
0*
#4370000
1(
08
1*
#4380000
0*
#4390000
b1101100 9
0(
18
1*
#4400000
0*
#4410000
1(
08
1*
#4420000
0*
#4430000
b1101101 9
0(
18
1*
#4440000
0*
#4450000
1(
08
1*
#4460000
0*
#4470000
b1101110 9
0(
18
1*
#4480000
0*
#4490000
1(
08
1*
#4500000
0*
#4510000
b1101111 9
0(
18
1*
#4520000
0*
#4530000
1(
08
1*
#4540000
0*
#4550000
b1110000 9
0(
18
1*
#4560000
0*
#4570000
1(
08
1*
#4580000
0*
#4590000
b1110001 9
0(
18
1*
#4600000
0*
#4610000
1(
08
1*
#4620000
0*
#4630000
b1110010 9
0(
18
1*
#4640000
0*
#4650000
1(
08
1*
#4660000
0*
#4670000
b1110011 9
0(
18
1*
#4680000
0*
#4690000
1(
08
1*
#4700000
0*
#4710000
b1110100 9
0(
18
1*
#4720000
0*
#4730000
1(
08
1*
#4740000
0*
#4750000
b1110101 9
0(
18
1*
#4760000
0*
#4770000
1(
08
1*
#4780000
0*
#4790000
b1110110 9
0(
18
1*
#4800000
0*
#4810000
1(
08
1*
#4820000
0*
#4830000
b1110111 9
0(
18
1*
#4840000
0*
#4850000
1(
08
1*
#4860000
0*
#4870000
b1111000 9
0(
18
1*
#4880000
0*
#4890000
1(
08
1*
#4900000
0*
#4910000
b1111001 9
0(
18
1*
#4920000
0*
#4930000
1(
08
1*
#4940000
0*
#4950000
b1111010 9
0(
18
1*
#4960000
0*
#4970000
1(
08
1*
#4980000
0*
#4990000
b1111011 9
0(
18
1*
#5000000
0*
#5010000
1(
08
1*
#5020000
0*
#5030000
b1111100 9
0(
18
1*
#5040000
0*
#5050000
1(
08
1*
#5060000
0*
#5070000
b1111101 9
0(
18
1*
#5080000
0*
#5090000
1(
08
1*
#5100000
0*
#5110000
b1111110 9
0(
18
1*
#5120000
0*
#5130000
1(
08
1*
#5140000
0*
#5150000
b1111111 9
0(
18
1*
#5160000
0*
#5170000
1(
08
1*
#5180000
0*
#5190000
b0 &
b0 6
b10 ;
0'
b10000000 9
0(
18
1*
#5200000
0*
#5210000
1(
08
1*
#5220000
0*
#5230000
b10000001 9
0(
18
1*
#5240000
0*
#5250000
1(
08
1*
#5260000
0*
#5270000
b10000010 9
0(
18
1*
#5280000
0*
#5290000
1(
08
1*
#5300000
0*
#5310000
b10000011 9
0(
18
1*
#5320000
0*
#5330000
1(
08
1*
#5340000
0*
#5350000
b10000100 9
0(
18
1*
#5360000
0*
#5370000
1(
08
1*
#5380000
0*
#5390000
b10000101 9
0(
18
1*
#5400000
0*
#5410000
1(
08
1*
#5420000
0*
#5430000
b10000110 9
0(
18
1*
#5440000
0*
#5450000
1(
08
1*
#5460000
0*
#5470000
b10000111 9
0(
18
1*
#5480000
0*
#5490000
1(
08
1*
#5500000
0*
#5510000
1%
b10001000 9
0(
18
1*
#5520000
0*
#5530000
1(
08
1*
#5540000
0*
#5550000
b10001001 9
0(
18
1*
#5560000
0*
#5570000
1(
08
1*
#5580000
0*
#5590000
b10001010 9
0(
18
1*
#5600000
0*
#5610000
1(
08
1*
#5620000
0*
#5630000
b10001011 9
0(
18
1*
#5640000
0*
#5650000
1(
08
1*
#5660000
0*
#5670000
b10001100 9
0(
18
1*
#5680000
0*
#5690000
1(
08
1*
#5700000
0*
#5710000
b10001101 9
0(
18
1*
#5720000
0*
#5730000
1(
08
1*
#5740000
0*
#5750000
b10001110 9
0(
18
1*
#5760000
0*
#5770000
1(
08
1*
#5780000
0*
#5790000
b10001111 9
0(
18
1*
#5800000
0*
#5810000
1(
08
1*
#5820000
0*
#5830000
b11111111 $
b11111111 7
b0 ;
0%
1'
b1 :
b0 9
0(
18
1*
#5840000
0*
#5850000
1(
08
1*
#5860000
0*
#5870000
b1 9
0(
18
1*
#5880000
0*
#5890000
1(
08
1*
#5900000
0*
#5910000
b10 9
0(
18
1*
#5920000
0*
#5930000
1(
08
1*
#5940000
0*
#5950000
b11 9
0(
18
1*
#5960000
0*
#5970000
1(
08
1*
#5980000
0*
#5990000
b100 9
0(
18
1*
#6000000
0*
#6010000
1(
08
1*
#6020000
0*
#6030000
b101 9
0(
18
1*
#6040000
0*
#6050000
1(
08
1*
#6060000
0*
#6070000
b110 9
0(
18
1*
#6080000
0*
#6090000
1(
08
1*
#6100000
0*
#6110000
b111 9
0(
18
1*
#6120000
0*
#6130000
1(
08
1*
#6140000
0*
#6150000
b1000 9
0(
18
1*
#6160000
0*
#6170000
1(
08
1*
#6180000
0*
#6190000
b1001 9
0(
18
1*
#6200000
0*
#6210000
1(
08
1*
#6220000
0*
#6230000
b1010 9
0(
18
1*
#6240000
0*
#6250000
1(
08
1*
#6260000
0*
#6270000
b1011 9
0(
18
1*
#6280000
0*
#6290000
1(
08
1*
#6300000
0*
#6310000
b1100 9
0(
18
1*
#6320000
0*
#6330000
1(
08
1*
#6340000
0*
#6350000
b1101 9
0(
18
1*
#6360000
0*
#6370000
1(
08
1*
#6380000
0*
#6390000
b1110 9
0(
18
1*
#6400000
0*
#6410000
1(
08
1*
#6420000
0*
#6430000
b1111 9
0(
18
1*
#6440000
0*
#6450000
1(
08
1*
#6460000
0*
#6470000
b10000 9
0(
18
1*
#6480000
0*
#6490000
1(
08
1*
#6500000
0*
#6510000
b10001 9
0(
18
1*
#6520000
0*
#6530000
1(
08
1*
#6540000
0*
#6550000
b10010 9
0(
18
1*
#6560000
0*
#6570000
1(
08
1*
#6580000
0*
#6590000
b10011 9
0(
18
1*
#6600000
0*
#6610000
1(
08
1*
#6620000
0*
#6630000
b10100 9
0(
18
1*
#6640000
0*
#6650000
1(
08
1*
#6660000
0*
#6670000
b10101 9
0(
18
1*
#6680000
0*
#6690000
1(
08
1*
#6700000
0*
#6710000
b10110 9
0(
18
1*
#6720000
0*
#6730000
1(
08
1*
#6740000
0*
#6750000
b10111 9
0(
18
1*
#6760000
0*
#6770000
1(
08
1*
#6780000
0*
#6790000
b11000 9
0(
18
1*
#6800000
0*
#6810000
1(
08
1*
#6820000
0*
#6830000
b11001 9
0(
18
1*
#6840000
0*
#6850000
1(
08
1*
#6860000
0*
#6870000
b11010 9
0(
18
1*
#6880000
0*
#6890000
1(
08
1*
#6900000
0*
#6910000
b11011 9
0(
18
1*
#6920000
0*
#6930000
1(
08
1*
#6940000
0*
#6950000
b11100 9
0(
18
1*
#6960000
0*
#6970000
1(
08
1*
#6980000
0*
#6990000
b11101 9
0(
18
1*
#7000000
0*
#7010000
1(
08
1*
#7020000
0*
#7030000
b11110 9
0(
18
1*
#7040000
0*
#7050000
1(
08
1*
#7060000
0*
#7070000
b11111 9
0(
18
1*
#7080000
0*
#7090000
1(
08
1*
#7100000
0*
#7110000
b100000 9
0(
18
1*
#7120000
0*
#7130000
1(
08
1*
#7140000
0*
#7150000
b100001 9
0(
18
1*
#7160000
0*
#7170000
1(
08
1*
#7180000
0*
#7190000
b100010 9
0(
18
1*
#7200000
0*
#7210000
1(
08
1*
#7220000
0*
#7230000
b100011 9
0(
18
1*
#7240000
0*
#7250000
1(
08
1*
#7260000
0*
#7270000
b100100 9
0(
18
1*
#7280000
0*
#7290000
1(
08
1*
#7300000
0*
#7310000
b100101 9
0(
18
1*
#7320000
0*
#7330000
1(
08
1*
#7340000
0*
#7350000
b100110 9
0(
18
1*
#7360000
0*
#7370000
1(
08
1*
#7380000
0*
#7390000
b100111 9
0(
18
1*
#7400000
0*
#7410000
1(
08
1*
#7420000
0*
#7430000
b101000 9
0(
18
1*
#7440000
0*
#7450000
1(
08
1*
#7460000
0*
#7470000
b101001 9
0(
18
1*
#7480000
0*
#7490000
1(
08
1*
#7500000
0*
#7510000
b101010 9
0(
18
1*
#7520000
0*
#7530000
1(
08
1*
#7540000
0*
#7550000
b101011 9
0(
18
1*
#7560000
0*
#7570000
1(
08
1*
#7580000
0*
#7590000
b101100 9
0(
18
1*
#7600000
0*
#7610000
1(
08
1*
#7620000
0*
#7630000
b101101 9
0(
18
1*
#7640000
0*
#7650000
1(
08
1*
#7660000
0*
#7670000
b101110 9
0(
18
1*
#7680000
0*
#7690000
1(
08
1*
#7700000
0*
#7710000
b101111 9
0(
18
1*
#7720000
0*
#7730000
1(
08
1*
#7740000
0*
#7750000
b110000 9
0(
18
1*
#7760000
0*
#7770000
1(
08
1*
#7780000
0*
#7790000
b110001 9
0(
18
1*
#7800000
0*
#7810000
1(
08
1*
#7820000
0*
#7830000
b110010 9
0(
18
1*
#7840000
0*
#7850000
1(
08
1*
#7860000
0*
#7870000
b110011 9
0(
18
1*
#7880000
0*
#7890000
1(
08
1*
#7900000
0*
#7910000
b110100 9
0(
18
1*
#7920000
0*
#7930000
1(
08
1*
#7940000
0*
#7950000
b110101 9
0(
18
1*
#7960000
0*
#7970000
1(
08
1*
#7980000
0*
#7990000
b110110 9
0(
18
1*
#8000000
0*
#8010000
1(
08
1*
#8020000
0*
#8030000
b110111 9
0(
18
1*
#8040000
0*
#8050000
1(
08
1*
#8060000
0*
#8070000
b111000 9
0(
18
1*
#8080000
0*
#8090000
1(
08
1*
#8100000
0*
#8110000
b111001 9
0(
18
1*
#8120000
0*
#8130000
1(
08
1*
#8140000
0*
#8150000
b111010 9
0(
18
1*
#8160000
0*
#8170000
1(
08
1*
#8180000
0*
#8190000
b111011 9
0(
18
1*
#8200000
0*
#8210000
1(
08
1*
#8220000
0*
#8230000
b111100 9
0(
18
1*
#8240000
0*
#8250000
1(
08
1*
#8260000
0*
#8270000
b111101 9
0(
18
1*
#8280000
0*
#8290000
1(
08
1*
#8300000
0*
#8310000
b111110 9
0(
18
1*
#8320000
0*
#8330000
1(
08
1*
#8340000
0*
#8350000
b111111 9
0(
18
1*
#8360000
0*
#8370000
1(
08
1*
#8380000
0*
#8390000
b11111111 &
b11111111 6
b0 $
b0 7
b1 ;
b1000000 9
0(
18
1*
#8400000
0*
#8410000
1(
08
1*
#8420000
0*
#8430000
b1000001 9
0(
18
1*
#8440000
0*
#8450000
1(
08
1*
#8460000
0*
#8470000
b1000010 9
0(
18
1*
#8480000
0*
#8490000
1(
08
1*
#8500000
0*
#8510000
b1000011 9
0(
18
1*
#8520000
0*
#8530000
1(
08
1*
#8540000
0*
#8550000
b1000100 9
0(
18
1*
#8560000
0*
#8570000
1(
08
1*
#8580000
0*
#8590000
b1000101 9
0(
18
1*
#8600000
0*
#8610000
1(
08
1*
#8620000
0*
#8630000
b1000110 9
0(
18
1*
#8640000
0*
#8650000
1(
08
1*
#8660000
0*
#8670000
b1000111 9
0(
18
1*
#8680000
0*
#8690000
1(
08
1*
#8700000
0*
#8710000
b1001000 9
0(
18
1*
#8720000
0*
#8730000
1(
08
1*
#8740000
0*
#8750000
b1001001 9
0(
18
1*
#8760000
0*
#8770000
1(
08
1*
#8780000
0*
#8790000
b1001010 9
0(
18
1*
#8800000
0*
#8810000
1(
08
1*
#8820000
0*
#8830000
b1001011 9
0(
18
1*
#8840000
0*
#8850000
1(
08
1*
#8860000
0*
#8870000
b1001100 9
0(
18
1*
#8880000
0*
#8890000
1(
08
1*
#8900000
0*
#8910000
b1001101 9
0(
18
1*
#8920000
0*
#8930000
1(
08
1*
#8940000
0*
#8950000
b1001110 9
0(
18
1*
#8960000
0*
#8970000
1(
08
1*
#8980000
0*
#8990000
b1001111 9
0(
18
1*
#9000000
0*
#9010000
1(
08
1*
#9020000
0*
#9030000
b1010000 9
0(
18
1*
#9040000
0*
#9050000
1(
08
1*
#9060000
0*
#9070000
b1010001 9
0(
18
1*
#9080000
0*
#9090000
1(
08
1*
#9100000
0*
#9110000
b1010010 9
0(
18
1*
#9120000
0*
#9130000
1(
08
1*
#9140000
0*
#9150000
b1010011 9
0(
18
1*
#9160000
0*
#9170000
1(
08
1*
#9180000
0*
#9190000
b1010100 9
0(
18
1*
#9200000
0*
#9210000
1(
08
1*
#9220000
0*
#9230000
b1010101 9
0(
18
1*
#9240000
0*
#9250000
1(
08
1*
#9260000
0*
#9270000
b1010110 9
0(
18
1*
#9280000
0*
#9290000
1(
08
1*
#9300000
0*
#9310000
b1010111 9
0(
18
1*
#9320000
0*
#9330000
1(
08
1*
#9340000
0*
#9350000
b1011000 9
0(
18
1*
#9360000
0*
#9370000
1(
08
1*
#9380000
0*
#9390000
b1011001 9
0(
18
1*
#9400000
0*
#9410000
1(
08
1*
#9420000
0*
#9430000
b1011010 9
0(
18
1*
#9440000
0*
#9450000
1(
08
1*
#9460000
0*
#9470000
b1011011 9
0(
18
1*
#9480000
0*
#9490000
1(
08
1*
#9500000
0*
#9510000
b1011100 9
0(
18
1*
#9520000
0*
#9530000
1(
08
1*
#9540000
0*
#9550000
b1011101 9
0(
18
1*
