HDMI_to_Matrix_FPGA/HDMI_to_Matrix/src/b_color_batch_buffer/Color_Batch_Buffer.sv
module Color_Batch_Buffer #(
    parameter int BATCH_SIZE = 8
)(
    input logic I_rgb_clk,
    input logic I_rst_n,

    input logic [7:0] I_color,
    input logic I_color_valid,

    output logic O_batch_ready,
    output logic O_batch_clk_out,
    output logic [8*BATCH_SIZE-1:0] O_batch_color
);


    // Lokale Parameter
    localparam int WRITE_POINTER_WIDTH = $clog2(BATCH_SIZE)+1;


    // Internal double Buffer
    logic [7:0] color_buffer [1:0][BATCH_SIZE-1:0];  // Two buffers with BATCH_SIZE colors each
    // control register
    logic active_buffer;
    logic [WRITE_POINTER_WIDTH-1:0] write_ptr;
    logic output_valid;


    // Write logic
    always_ff @(posedge I_rgb_clk or negedge I_rst_n) begin
        if (!I_rst_n) begin
            active_buffer <= 0;
            write_ptr <= 0; //BATCH_SIZE - 1;  // Start at the end of the buffer
            output_valid <= 0;
        end else begin
            if (I_color_valid) begin
                color_buffer[active_buffer][write_ptr] <= I_color;
                
                if (write_ptr == BATCH_SIZE - 1) begin
                    write_ptr <= 0;
                    output_valid <= 1;
                    active_buffer <= ~active_buffer;  // Switch to the other buffer
                end else begin
                    write_ptr <= write_ptr + 1;
                    output_valid <= 0;
                end
            end else begin
                output_valid <= 0;
            end
        end
    end

    // Output logic
    assign O_batch_ready = output_valid && (write_ptr == 0);
    assign O_batch_clk_out = ~O_batch_ready; // Invert the batch ready signal for the output clock

    always_comb begin
        for (int i = 0; i < BATCH_SIZE; i++) begin
            O_batch_color[i*8 +: 8] = color_buffer[~active_buffer][i];
        end
    end

endmodule

HDMI_to_Matrix_FPGA/HDMI_to_Matrix/src/b_input_logic/b_color_batch_buffer/Color_Batch_Buffer_tb.sv
`timescale 1ns / 1ps

module Color_Batch_Buffer_tb;

    // Parameter
    localparam int BATCH_SIZE = 8;

    // Clock & Reset
    logic rgb_clk = 0;
    logic rst_n = 0;

    // Inputs
    logic [7:0] I_color;
    logic       I_color_valid;

    // Outputs
    logic       batch_ready;
    logic       batch_clk_out;
    logic [8*BATCH_SIZE-1:0] batch_color;

    // Clock Generator (e.g. 50 MHz)
    always #10 rgb_clk = ~rgb_clk;

    // DUT
    Color_Batch_Buffer #(
        .BATCH_SIZE(BATCH_SIZE)
    ) dut (
        .I_rgb_clk        (rgb_clk),
        .I_rst_n          (rst_n),
        .I_color        (I_color),
        .I_color_valid  (I_color_valid),
        .O_batch_ready  (batch_ready),
        .O_batch_clk_out (batch_clk_out),
        .O_batch_color  (batch_color)
    );

    int unsigned color_counter = 1;

    // Stimulus
    initial begin
        // Reset
        I_color        = 0;
        I_color_valid  = 0;
        #50;
        rst_n = 1;
        #20;

        // Send zwei vollständige Batches


        repeat (4) begin
            for (int i = 0; i < BATCH_SIZE; i++) begin

                @(negedge rgb_clk);
                I_color       = color_counter[7:0];
                color_counter++;
                I_color_valid = 1;
            end
            // @(posedge rgb_clk);
            // I_color_valid = 0;
            // #100;
        end


        // Simulation beenden
        #100;
        $finish;
    end

    // VCD-Output für GTKWave / iverilog
    initial begin
        $dumpfile("Color_Batch_Buffer_tb.vcd");
        $dumpvars(0, Color_Batch_Buffer_tb);
    end

endmodule

HDMI_to_Matrix_FPGA/HDMI_to_Matrix/sim/Color_Batch_Buffer_tb.vcd
$date
	Sat Apr 19 00:00:15 2025
$end
$version
	Icarus Verilog
$end
$timescale
	1ps
$end
$scope module Color_Batch_Buffer_tb $end
$var wire 1 ! batch_ready $end
$var wire 64 " batch_color [63:0] $end
$var wire 1 # batch_clk_out $end
$var parameter 32 $ BATCH_SIZE $end
$var reg 8 % I_color [7:0] $end
$var reg 1 & I_color_valid $end
$var reg 1 ' rgb_clk $end
$var reg 1 ( rst_n $end
$var reg 32 ) color_counter [31:0] $end
$scope module dut $end
$var wire 8 * I_color [7:0] $end
$var wire 1 & I_color_valid $end
$var wire 1 ' I_rgb_clk $end
$var wire 1 ( I_rst_n $end
$var wire 1 # O_batch_clk_out $end
$var wire 1 ! O_batch_ready $end
$var parameter 32 + BATCH_SIZE $end
$var parameter 32 , WRITE_POINTER_WIDTH $end
$var reg 64 - O_batch_color [63:0] $end
$var reg 1 . active_buffer $end
$var reg 1 / output_valid $end
$var reg 4 0 write_ptr [3:0] $end
$scope begin $ivl_for_loop0 $end
$var integer 32 1 i [31:0] $end
$upscope $end
$upscope $end
$scope begin $ivl_for_loop1 $end
$var integer 32 2 i [31:0] $end
$upscope $end
$upscope $end
$enddefinitions $end
$comment Show the parameter values. $end
$dumpall
b100 ,
b1000 +
b1000 $
$end
#0
$dumpvars
b0 2
b1000 1
bx 0
x/
x.
bx -
b0 *
b1 )
0(
0'
0&
b0 %
x#
bx "
x!
$end
#10000
1#
0!
b1000 1
0/
b0 0
0.
1'
#20000
0'
#30000
1'
#40000
0'
#50000
1'
1(
#60000
0'
#70000
1'
#80000
b1 2
1&
b10 )
b1 %
b1 *
0'
#90000
b1000 1
b1 0
1'
#100000
b10 2
b11 )
b10 %
b10 *
0'
#110000
b1000 1
b10 0
1'
#120000
b11 2
b100 )
b11 %
b11 *
0'
#130000
b1000 1
b11 0
1'
#140000
b100 2
b101 )
b100 %
b100 *
0'
#150000
b1000 1
b100 0
1'
#160000
b101 2
b110 )
b101 %
b101 *
0'
#170000
b1000 1
b101 0
1'
#180000
b110 2
b111 )
b110 %
b110 *
0'
#190000
b1000 1
b110 0
1'
#200000
b111 2
b1000 )
b111 %
b111 *
0'
#210000
b1000 1
b111 0
1'
#220000
b0 2
b1001 )
b1000 %
b1000 *
0'
#230000
0#
1!
b100000000111000001100000010100000100000000110000001000000001 "
b100000000111000001100000010100000100000000110000001000000001 -
b1000 1
1.
1/
b0 0
1'
#240000
b1 2
b1010 )
b1001 %
b1001 *
0'
#250000
1#
0!
b1000 1
0/
b1 0
1'
#260000
b10 2
b1011 )
b1010 %
b1010 *
0'
#270000
b1000 1
b10 0
1'
#280000
b11 2
b1100 )
b1011 %
b1011 *
0'
#290000
b1000 1
b11 0
1'
#300000
b100 2
b1101 )
b1100 %
b1100 *
0'
#310000
b1000 1
b100 0
1'
#320000
b101 2
b1110 )
b1101 %
b1101 *
0'
#330000
b1000 1
b101 0
1'
#340000
b110 2
b1111 )
b1110 %
b1110 *
0'
#350000
b1000 1
b110 0
1'
#360000
b111 2
b10000 )
b1111 %
b1111 *
0'
#370000
b1000 1
b111 0
1'
#380000
b0 2
b10001 )
b10000 %
b10000 *
0'
#390000
0#
1!
b1000000001111000011100000110100001100000010110000101000001001 "
b1000000001111000011100000110100001100000010110000101000001001 -
b1000 1
0.
1/
b0 0
1'
#400000
b1 2
b10010 )
b10001 %
b10001 *
0'
#410000
1#
0!
b1000 1
0/
b1 0
1'
#420000
b10 2
b10011 )
b10010 %
b10010 *
0'
#430000
b1000 1
b10 0
1'
#440000
b11 2
b10100 )
b10011 %
b10011 *
0'
#450000
b1000 1
b11 0
1'
#460000
b100 2
b10101 )
b10100 %
b10100 *
0'
#470000
b1000 1
b100 0
1'
#480000
b101 2
b10110 )
b10101 %
b10101 *
0'
#490000
b1000 1
b101 0
1'
#500000
b110 2
b10111 )
b10110 %
b10110 *
0'
#510000
b1000 1
b110 0
1'
#520000
b111 2
b11000 )
b10111 %
b10111 *
0'
#530000
b1000 1
b111 0
1'
#540000
b0 2
b11001 )
b11000 %
b11000 *
0'
#550000
0#
1!
b1100000010111000101100001010100010100000100110001001000010001 "
b1100000010111000101100001010100010100000100110001001000010001 -
b1000 1
1.
1/
b0 0
1'
#560000
b1 2
b11010 )
b11001 %
b11001 *
0'
#570000
1#
0!
b1000 1
0/
b1 0
1'
#580000
b10 2
b11011 )
b11010 %
b11010 *
0'
#590000
b1000 1
b10 0
1'
#600000
b11 2
b11100 )
b11011 %
b11011 *
0'
#610000
b1000 1
b11 0
1'
#620000
b100 2
b11101 )
b11100 %
b11100 *
0'
#630000
b1000 1
b100 0
1'
#640000
b101 2
b11110 )
b11101 %
b11101 *
0'
#650000
b1000 1
b101 0
1'
#660000
b110 2
b11111 )
b11110 %
b11110 *
0'
#670000
b1000 1
b110 0
1'
#680000
b111 2
b100000 )
b11111 %
b11111 *
0'
#690000
b1000 1
b111 0
1'
#700000
b1000 2
b100001 )
b100000 %
b100000 *
0'
#710000
0#
1!
b10000000011111000111100001110100011100000110110001101000011001 "
b10000000011111000111100001110100011100000110110001101000011001 -
b1000 1
0.
1/
b0 0
1'
#720000
0'
#730000
1#
0!
b1000 1
0/
b1 0
1'
#740000
0'
#750000
b1000 1
b10 0
1'
#760000
0'
#770000
b1000 1
b11 0
1'
#780000
0'
#790000
b1000 1
b100 0
1'
